{
"boy_page_url": "https://boyawards.secure-platform.com/a/gallery/rounds/12/details/10563",
"category": "Product > accessories",
"company_name": "oOumm",
"company_url": "www.ooumm.com",
"description_html": "LIBRA (design by Dan Yeffet)<br/>Libra is both unique and familiar, refering to the aesthetic of XIXth century lanterns as well as the codes of incense burners. A photophore made of too pieces of blown glass that fit, n'est and light up each other. Standing on top, the scented candle completes with elegance the \u00e9difice.",
"id": "10563",
"product_name": "Libra",
"video_url": ""
}