{
"boy_page_url": "https://boyawards.secure-platform.com/a/gallery/rounds/12/details/10807",
"category": "Product > textiles: residential",
"company_name": "AREA",
"company_url": "areahome.com",
"description_html": "OVAL- 100% cotton Jacquard Duvet Covers &amp; Shams a soft geometric 4 color weave.<br/>This design is loosely inspired of Art Deco and works of Wiener Werkst\u00e4tte.<br/>Original made of pencil &amp; watercolor sketches aiming for something both bold and quiet.<br/>Its made in Portugal and was introduced in NY in August.",
"id": "10807",
"product_name": "OVAL",
"video_url": ""
}