{
"boy_page_url": "https://boyawards.secure-platform.com/a/gallery/rounds/12/details/11017",
"category": "Product > seating: residential/lounge",
"company_name": "Phase Design",
"company_url": "www.phasedesignonline.com",
"description_html": "The Kickstand Lounge Chair is a lounge chair where upholstery sits atop powder coated metal bases. Each piece is accentuated with a deliberate solid brass bar detail, and a contrasting head rest. As with all of our existing collections, these pieces are made locally in Southern California.",
"id": "11017",
"product_name": "Kickstand Lounge Chair",
"video_url": ""
}