{
"boy_page_url": "https://boyawards.secure-platform.com/a/gallery/rounds/12/details/8119",
"category": "Product > textiles: hospitality",
"company_name": "Kravet Contract",
"company_url": "kravetcontract.com",
"description_html": "Kravet Contract introduces a new Guaranteed in Stock program featuring value priced upholstery targeted for performance and style.<br/><br/>Thirteen playful patterns and textures are featured along 85 color combinations. Ranging from soft and serene to bold candy color combinations this collection features multi-color patterns and textures all priced to fit tight budgets. <br/><br/>Exceeding all ACT standards for performance, budget priced and guaranteed in stock, this collection is sure to hit a sweet spot.",
"id": "8119",
"product_name": "Guaranteed in Stock Value Weaves",
"video_url": ""
}