{
"boy_page_url": "https://boyawards.secure-platform.com/a/gallery/rounds/12/details/8645",
"category": "Product > wall covering: tile and stone",
"company_name": "ANN SACKS",
"company_url": "www.annsacks.com",
"description_html": "ANN SACKS illusionary Ermanno is a metallic glazed porcelain tile that features two intricate, two-shade repeat designs and a contrasting singular color design. Ermanno is crafted in Italy and exclusive to ANN SACKS in the United States. Inspired by Art Deco design, Ermanno has slight variations in color and irregularities within the pattern resulting in an organic, handcrafted appearance. Ermanno\u2019s two patterns feature a rich palette of various color combinations. The Pavone and Geometric designs are offered in Gold on Black, Gold on White, Silver on Black, Silver on White, or stand-alone White. Trama is available in Bronze on Black or Bronze on White.<br/>This completely in-stock program accommodates the tightest of installation schedules for large-scale commercial projects as well as the striking appearance required to create sensational residential applications.",
"id": "8645",
"product_name": "Ermanno",
"video_url": ""
}